LICENSE
MANIFEST.in
README.rst
setup.py
widgy_blog/__init__.py
widgy_blog/admin.py
widgy_blog/models.py
widgy_blog/search_indexes.py
widgy_blog/site.py
widgy_blog/sitemaps.py
widgy_blog/urls.py
widgy_blog/version.py
widgy_blog/views.py
widgy_blog.egg-info/PKG-INFO
widgy_blog.egg-info/SOURCES.txt
widgy_blog.egg-info/dependency_links.txt
widgy_blog.egg-info/not-zip-safe
widgy_blog.egg-info/requires.txt
widgy_blog.egg-info/top_level.txt
widgy_blog/migrations/0001_initial.py
widgy_blog/migrations/0002_auto__add_field_bloglayout_description__add_field_bloglayout_keywords_.py
widgy_blog/migrations/__init__.py
widgy_blog/templates/widgy/widgy_blog/archive_list.html
widgy_blog/templates/widgy/widgy_blog/blog_detail.html
widgy_blog/templates/widgy/widgy_blog/blog_list.html
widgy_blog/templates/widgy/widgy_blog/pagination.html